Metadata-Version: 2.1
Name: raz
Version: 0.1.1
Summary: Testing installation of Package
Home-page: https://github.com/samansiadati/raz
Author: Saman Siadati
Author-email: siadatisaman@gmail.com
License: MIT
Download-URL: https://github.com/samansiadati/raz/archive/refs/tags/raz.tar.gz
Project-URL: Bug Tracker, https://github.com/samansiadati/raz/issues
Keywords: pandas,manipulation,raz
Platform: UNKNOWN
Classifier: Development Status :: 3 - Alpha
Classifier: Intended Audience :: Developers
Classifier: Topic :: Software Development :: Documentation
Classifier: License :: OSI Approved :: MIT License
Classifier: Programming Language :: Python :: 3.8
